dora_opus/__init__.py
dora_opus/main.py
dora_opus-0.3.11.dist-info/METADATA
dora_opus-0.3.11.dist-info/WHEEL
dora_opus-0.3.11.dist-info/entry_points.txt
dora_opus-0.3.11.dist-info/top_level.txt
dora_opus-0.3.11.dist-info/RECORD
