Metadata-Version: 2.4
Name: dora-opus
Version: 0.3.11
Summary: Dora Node for Text translating using Opus
Author-email: Haixuan Xavier Tao <tao.xavier@outlook.com>, Enzo Le Van <dev@enzo-le-van.fr>, Félix Huang <felix.huang.net@gmail.com>
License: MIT
Requires-Python: >=3.8
Requires-Dist: dora-rs>=0.3.9
Requires-Dist: numpy<2.0.0
Requires-Dist: transformers>=4.45
Requires-Dist: modelscope>=1.18.1
Requires-Dist: sentencepiece>=0.1.99
Requires-Dist: torch>=2.2.0
Requires-Dist: sacremoses>=0.1.1
